zeus_apple_silicon-1.0.4.dist-info/RECORD
zeus_apple_silicon-1.0.4.dist-info/WHEEL
zeus_apple_silicon-1.0.4.dist-info/METADATA
zeus_apple_silicon-1.0.4.dist-info/licenses/LICENSE
zeus_apple_silicon/zeus_ext.pypy39-pp73-darwin.so
zeus_apple_silicon/__init__.py
