Metadata-Version: 2.1
Name: zeus-apple-silicon
Version: 1.0.4
Summary: A library for programmatic, in-code energy measurement on Apple Silicon.
Keywords: apple,apple-silicon,macos,energy,mlsys,deep-learning
Author: Zeus Team
License: Apache 2.0
Classifier: License :: OSI Approved :: Apache Software License
Classifier: Topic :: Scientific/Engineering :: Artificial Intelligence
Classifier: Programming Language :: Python :: 3.9
Classifier: Programming Language :: Python :: 3.10
Classifier: Programming Language :: Python :: 3.11
Classifier: Programming Language :: Python :: 3.12
Classifier: Programming Language :: Python :: 3.13
Project-URL: Repository, https://github.com/ml-energy/zeus-apple-silicon
Project-URL: Homepage, https://ml.energy/zeus
Project-URL: Documentation, https://ml.energy/zeus
Requires-Python: >=3.9
Provides-Extra: lint
Requires-Dist: ruff; extra == "lint"
Requires-Dist: pyright!=1.1.395; extra == "lint"
Provides-Extra: test
Requires-Dist: pytest; extra == "test"
Provides-Extra: dev
Requires-Dist: zeus-apple-silicon[lint,test]; extra == "dev"
